sphinxcontrib_fsharp-0.3.1-py3.7-nspkg.pth
sphinxcontrib/fsharp/__init__.py
sphinxcontrib/fsharp/autodocumenters.py
sphinxcontrib/fsharp/domain.py
sphinxcontrib_fsharp-0.3.1.dist-info/LICENCE.txt
sphinxcontrib_fsharp-0.3.1.dist-info/METADATA
sphinxcontrib_fsharp-0.3.1.dist-info/WHEEL
sphinxcontrib_fsharp-0.3.1.dist-info/namespace_packages.txt
sphinxcontrib_fsharp-0.3.1.dist-info/top_level.txt
sphinxcontrib_fsharp-0.3.1.dist-info/RECORD
