Metadata-Version: 2.1
Name: sphinxcontrib-fsharp
Version: 0.3.1
Summary: Sphinx extension to document F# libraries
Home-page: http://github.com/dbrattli/sphinx-fsharp
Author: Dag Brattli
Author-email: dag@brattli.net
License: MIT
Platform: UNKNOWN
Classifier: Development Status :: 2 - Pre-Alpha
Classifier: Intended Audience :: Developers
Classifier: License :: OSI Approved
Classifier: License :: OSI Approved :: MIT License
Classifier: Operating System :: OS Independent
Classifier: Programming Language :: Python
Classifier: Topic :: Documentation
Classifier: Topic :: Documentation :: Sphinx
